wg_conf/__init__.py
wg_conf-1.0.0.dist-info/LICENSE
wg_conf-1.0.0.dist-info/METADATA
wg_conf-1.0.0.dist-info/WHEEL
wg_conf-1.0.0.dist-info/top_level.txt
wg_conf-1.0.0.dist-info/RECORD
