Metadata-Version: 2.1
Name: wg-conf
Version: 1.0.0
Summary: Manage Wireguard configuration files
Home-page: https://github.com/galenguyer/wg_conf
Author: Galen Guyer
Author-email: galen@galenguyer.com
License: UNKNOWN
Platform: UNKNOWN
Classifier: Programming Language :: Python
Classifier: Programming Language :: Python :: 3
Classifier: License :: OSI Approved :: MIT License
Classifier: Operating System :: OS Independent
Classifier: Development Status :: 5 - Production/Stable
Requires-Python: >=3.6
